quiltz/__init__.py
quiltz/anonymizer.py
quiltz/parsers.py
quiltz/results.py
quiltz/validator.py
quiltz/version.py
quiltz/id/__init__.py
quiltz/id/id.py
quiltz/id/testbuilders.py
quiltz-0.3.0.dist-info/LICENSE
quiltz-0.3.0.dist-info/METADATA
quiltz-0.3.0.dist-info/WHEEL
quiltz-0.3.0.dist-info/top_level.txt
quiltz-0.3.0.dist-info/RECORD
