Metadata-Version: 2.1
Name: quiltz
Version: 0.3.0
Summary: A domain utility module for python
Home-page: https://github.com/qwaneu/quiltz
Author: Rob Westgeest
Author-email: rob@qwan.eu
License: UNKNOWN
Platform: UNKNOWN
Classifier: Programming Language :: Python :: 3
Classifier: License :: OSI Approved :: MIT License
Classifier: Operating System :: OS Independent
